glpi/__init__.py
glpi/glpi.py
glpi/glpi_item.py
glpi/item_knowbase.py
glpi/item_profile.py
glpi/item_ticket.py
glpi/version.py
glpi-0.4.0.dist-info/LICENSE
glpi-0.4.0.dist-info/METADATA
glpi-0.4.0.dist-info/WHEEL
glpi-0.4.0.dist-info/top_level.txt
glpi-0.4.0.dist-info/RECORD
